ipfs_api_mount/__init__.py
ipfs_api_mount/commands.py
ipfs_api_mount/ipfs.py
ipfs_api_mount/ipfs_mounted.py
ipfs_api_mount/unixfs_pb2.py
ipfs_api_mount/version.py
ipfs_api_mount/fuse_operations/__init__.py
ipfs_api_mount/fuse_operations/high.py
ipfs_api_mount/fuse_operations/high_whole.py
ipfs_api_mount-0.4.1.data/scripts/ipfs-api-mount
ipfs_api_mount-0.4.1.data/scripts/ipfs-api-mount-whole
ipfs_api_mount-0.4.1.dist-info/LICENSE
ipfs_api_mount-0.4.1.dist-info/METADATA
ipfs_api_mount-0.4.1.dist-info/WHEEL
ipfs_api_mount-0.4.1.dist-info/top_level.txt
ipfs_api_mount-0.4.1.dist-info/RECORD
