Metadata-Version: 2.1
Name: ipfs-api-mount
Version: 0.4.1
Summary: Mount IPFS directory as local FS.
Home-page: https://github.com/SupraSummus/ipfs-api-mount
Author: UNKNOWN
Author-email: UNKNOWN
License: MIT
Keywords: ipfs fuse mount fs
Platform: UNKNOWN
Classifier: Topic :: System :: Filesystems
Requires-Dist: fusepy (==3.0.*)
Requires-Dist: ipfshttpclient (<0.8,>=0.6.1)
Requires-Dist: lru-dict (==1.*)
Requires-Dist: protobuf (<4,>=3.15)
Requires-Dist: py-multibase (==1.*)
